{"_typename":"data_vizConfig_t","maxFps":60,"realtime":1,"windowWidth":800,"windowHeight":600,"cameraPos":{"_typename":"data_vector3_t","v":[-1.000000000000,0.000000000000,0.000000000000]},"cameraPoint":{"_typename":"data_vector3_t","v":[0.000000000000,0.000000000000,0.000000000000]},"mousePick":0,"numMeshProps":10,"meshProps":[{"_typename":"data_vizMeshProperties_t","bodyId":18,"color":{"_typename":"data_vector4_t","v":[0.500000000000,0.500000000000,0.500000000000,1.000000000000]}},{"_typename":"data_vizMeshProperties_t","bodyId":16,"color":{"_typename":"data_vector4_t","v":[0.500000000000,0.500000000000,0.500000000000,1.000000000000]}},{"_typename":"data_vizMeshProperties_t","bodyId":14,"color":{"_typename":"data_vector4_t","v":[0.500000000000,0.500000000000,0.500000000000,1.000000000000]}},{"_typename":"data_vizMeshProperties_t","bodyId":12,"color":{"_typename":"data_vector4_t","v":[0.500000000000,0.500000000000,0.500000000000,1.000000000000]}},{"_typename":"data_vizMeshProperties_t","bodyId":0,"color":{"_typename":"data_vector4_t","v":[0.141176477075,0.682352960110,0.000000000000,1.000000000000]}},{"_typename":"data_vizMeshProperties_t","bodyId":10,"color":{"_typename":"data_vector4_t","v":[0.156862750649,0.156862750649,0.156862750649,1.000000000000]}},{"_typename":"data_vizMeshProperties_t","bodyId":8,"color":{"_typename":"data_vector4_t","v":[0.156862750649,0.156862750649,0.156862750649,1.000000000000]}},{"_typename":"data_vizMeshProperties_t","bodyId":6,"color":{"_typename":"data_vector4_t","v":[0.156862750649,0.156862750649,0.156862750649,1.000000000000]}},{"_typename":"data_vizMeshProperties_t","bodyId":4,"color":{"_typename":"data_vector4_t","v":[0.156862750649,0.156862750649,0.156862750649,1.000000000000]}},{"_typename":"data_vizMeshProperties_t","bodyId":2,"color":{"_typename":"data_vector4_t","v":[0.843137264252,0.000000000000,0.000000000000,1.000000000000]}}]}
